<?xml version="1.0" encoding="utf-8"?>
<openerp>
    <data noupdate="1">
    
      <record id="deduction_parameters_1" model="arul.hr.payroll.deduction.parameters">
          <field name="name">PF Deduction</field>
          <field name="code">PF.D</field>
      </record>
      
      <record id="deduction_parameters_2" model="arul.hr.payroll.deduction.parameters">
          <field name="name">Pension Deduction</field>
          <field name="code">P.D</field>
      </record>
      
      <record id="deduction_parameters_3" model="arul.hr.payroll.deduction.parameters">
          <field name="name">VPF Deduction</field>
          <field name="code">VPF.D</field>
      </record>
      
      <record id="deduction_parameters_4" model="arul.hr.payroll.deduction.parameters">
          <field name="name">ESI Deduction</field>
          <field name="code">ESI.D</field>
      </record>
      
      <record id="deduction_parameters_5" model="arul.hr.payroll.deduction.parameters">
          <field name="name">Food Deduction</field>
          <field name="code">F.D</field>
      </record>
      
      <record id="deduction_parameters_6" model="arul.hr.payroll.deduction.parameters">
          <field name="name">Loan Deduction</field>
          <field name="code">L.D</field>
      </record>
      
      <record id="deduction_parameters_7" model="arul.hr.payroll.deduction.parameters">
          <field name="name">Insurance Deduction</field>
          <field name="code">I.D</field>
      </record>
      
      <record id="deduction_parameters_8" model="arul.hr.payroll.deduction.parameters">
          <field name="name">Professional Tax</field>
          <field name="code">PT</field>
      </record>
      
      <record id="deduction_parameters_9" model="arul.hr.payroll.deduction.parameters">
          <field name="name">Labor Welfare Fund</field>
          <field name="code">LWF</field>
      </record>

	  <record id="deduction_parameters_11" model="arul.hr.payroll.deduction.parameters">
          <field name="name">Loss of Pay</field>
          <field name="code">LOP</field>
      </record>
      <!-- TPT start-->
      <record id="deduction_parameters_12" model="arul.hr.payroll.deduction.parameters">
          <field name="name">LIC Premium Insurance</field>
          <field name="code">INS_LIC_PREM</field>
      </record>
      <record id="deduction_parameters_13" model="arul.hr.payroll.deduction.parameters">
          <field name="name">Other Insurances</field>
          <field name="code">INS_OTHERS</field>
      </record>
      
      <record id="deduction_parameters_14" model="arul.hr.payroll.deduction.parameters">
          <field name="name">VVTi Loan</field>
          <field name="code">LOAN_VVTI</field>
      </record>
      
      <record id="deduction_parameters_15" model="arul.hr.payroll.deduction.parameters">
          <field name="name">LIC HFL Loan</field>
          <field name="code">LOAN_LIC_HFL</field>
      </record>
      <record id="deduction_parameters_16" model="arul.hr.payroll.deduction.parameters">
          <field name="name">HDFC Loan</field>
          <field name="code">LOAN_HDFC</field>
      </record>
      <record id="deduction_parameters_17" model="arul.hr.payroll.deduction.parameters">
          <field name="name">TMB Loan</field>
          <field name="code">LOAN_TMB</field>
      </record>
      <record id="deduction_parameters_18" model="arul.hr.payroll.deduction.parameters">
          <field name="name">SBT Loan</field>
          <field name="code">LOAN_SBT</field>
      </record>
      <record id="deduction_parameters_19" model="arul.hr.payroll.deduction.parameters">
          <field name="name">Other Loans</field>
          <field name="code">LOAN_OTHERS</field>
      </record>
      <record id="deduction_parameters_20" model="arul.hr.payroll.deduction.parameters">
          <field name="name">IT Deduction</field>
          <field name="code">IT</field>
      </record>
      <!-- TPT End -->
      <record id="deduction_parameters_10" model="arul.hr.payroll.deduction.parameters">
          <field name="name">Total Deduction</field>
          <field name="code">TOTAL_DEDUCTION</field>
      </record>
      
      <record id="deduction_parameters_21" model="arul.hr.payroll.deduction.parameters">
          <field name="name">Canteen Deduction</field>
          <field name="code">C.D</field>
      </record>
      
    </data>
</openerp>
